win_cur/__init__.py
win_cur/cursor.py
win_cur/test.py
win_cur-1.0.dist-info/licenses/LICENSE
win_cur-1.0.dist-info/METADATA
win_cur-1.0.dist-info/WHEEL
win_cur-1.0.dist-info/top_level.txt
win_cur-1.0.dist-info/RECORD
