Metadata-Version: 2.4
Name: win-cur
Version: 1.0
Summary: A library for manipulating Windows cursors, supporting CUR file reading and system cursor settings.
Home-page: https://github.com/hite4044/win-cur
Author: hite4044
License: MPL-2.0
Classifier: Development Status :: 3 - Alpha
Classifier: Programming Language :: Python :: 3
License-File: LICENSE
Dynamic: license-file
